monobiome/__init__.py
monobiome/__main__.py
monobiome/constants.py
monobiome/curve.py
monobiome/palette.py
monobiome/plotting.py
monobiome/scheme.py
monobiome/util.py
monobiome/cli/__init__.py
monobiome/cli/fill.py
monobiome/cli/palette.py
monobiome/cli/scheme.py
monobiome/data/parameters.toml
monobiome-1.5.0.dist-info/METADATA
monobiome-1.5.0.dist-info/WHEEL
monobiome-1.5.0.dist-info/entry_points.txt
monobiome-1.5.0.dist-info/top_level.txt
monobiome-1.5.0.dist-info/RECORD
