Metadata-Version: 2.4
Name: monobiome
Version: 1.5.0
Summary: Monobiome color palette
Author-email: Sam Griesemer <git@olog.io>
License-Expression: MIT
Project-URL: Homepage, https://doc.olog.io/monobiome
Project-URL: Documentation, https://doc.olog.io/monobiome
Project-URL: Repository, https://git.olog.io/olog/monobiome
Project-URL: Issues, https://git.olog.io/olog/monobiome/issues
Keywords: tempate-engine,color-palette
Classifier: Programming Language :: Python
Classifier: Operating System :: OS Independent
Classifier: Development Status :: 3 - Alpha
Classifier: Intended Audience :: Developers
Classifier: Intended Audience :: End Users/Desktop
Requires-Python: >=3.12
Requires-Dist: coloraide>=5.1
Requires-Dist: imageio[ffmpeg]>=2.37.2
Requires-Dist: kaleido>=1.1.0
Requires-Dist: matplotlib>=3.10.7
Requires-Dist: nbformat>=5.10.4
Requires-Dist: numpy>=2.3.4
Requires-Dist: pillow>=12.0.0
Requires-Dist: plotly>=6.3.1
Requires-Dist: pyqt5>=5.15.11
Requires-Dist: scipy>=1.16.2
Requires-Dist: symconf>=0.8.4
Provides-Extra: dev
Requires-Dist: ipykernel; extra == "dev"
Provides-Extra: doc
Requires-Dist: furo; extra == "doc"
Requires-Dist: myst-parser; extra == "doc"
Requires-Dist: sphinx; extra == "doc"
Requires-Dist: sphinx-togglebutton; extra == "doc"
Requires-Dist: sphinx-autodoc-typehints; extra == "doc"
Provides-Extra: test
Requires-Dist: pytest; extra == "test"
